pywencai/__init__.py
pywencai/convert.py
pywencai/headers.py
pywencai/hexin-v.bundle.js
pywencai/hexin-v.js
pywencai/package.json
pywencai/webpack.config.js
pywencai/wencai.py
pywencai-0.12.3.dist-info/LICENSE
pywencai-0.12.3.dist-info/METADATA
pywencai-0.12.3.dist-info/WHEEL
pywencai-0.12.3.dist-info/RECORD
