Metadata-Version: 2.1
Name: pywencai
Version: 0.12.3
Summary: 
Author: pluto
Author-email: mayuanchi1029@gmail.com
Requires-Python: >=3.8,<4.0
Classifier: Programming Language :: Python :: 3
Classifier: Programming Language :: Python :: 3.8
Classifier: Programming Language :: Python :: 3.9
Classifier: Programming Language :: Python :: 3.10
Classifier: Programming Language :: Python :: 3.11
Classifier: Programming Language :: Python :: 3.12
Classifier: Programming Language :: Python :: 3.13
Requires-Dist: PyExecJS (>=1.5.1,<2.0.0)
Requires-Dist: fake-useragent (>=1.1.1,<2.0.0)
Requires-Dist: pandas (>=1.5.0,<3.0.0)
Requires-Dist: pydash (>=7.0.3,<8.0.0)
Requires-Dist: requests
